youtuber/__init__.py
youtuber/api.py
youtuber/auto.py
youtuber/crawler.py
youtuber-0.1.4.dist-info/METADATA
youtuber-0.1.4.dist-info/WHEEL
youtuber-0.1.4.dist-info/top_level.txt
youtuber-0.1.4.dist-info/RECORD
