Metadata-Version: 2.1
Name: youtuber
Version: 0.1.4
Summary: Support tools including crawler, video editing, YouTube API, etc.
Home-page: https://github.com/DSDanielPark/youtuber
Author: parkminwoo
Author-email: parkminwoo1991@gmail.com
Requires-Python: >=3.6
Requires-Dist: selenium
Requires-Dist: google-api-python-client
Requires-Dist: pandas
